{
  "hash": "2c7141e7",
  "configHash": "452d3967",
  "lockfileHash": "9cbf85ee",
  "browserHash": "b6e097f3",
  "optimized": {
    "@vue/devtools-api": {
      "src": "../../../../node_modules/@vue/devtools-api/lib/esm/index.js",
      "file": "@vue_devtools-api.js",
      "fileHash": "5dbef2e9",
      "needsInterop": false
    },
    "@vuepress/shared": {
      "src": "../../../../node_modules/@vuepress/shared/dist/index.js",
      "file": "@vuepress_shared.js",
      "fileHash": "070317f9",
      "needsInterop": false
    },
    "vue": {
      "src": "../../../../node_modules/vue/dist/vue.runtime.esm-bundler.js",
      "file": "vue.js",
      "fileHash": "4b131d08",
      "needsInterop": false
    },
    "vue-router": {
      "src": "../../../../node_modules/vue-router/dist/vue-router.esm-bundler.js",
      "file": "vue-router.js",
      "fileHash": "13a89052",
      "needsInterop": false
    },
    "@theme/useDarkMode": {
      "src": "../../../../node_modules/@vuepress/theme-default/lib/client/composables/useDarkMode.js",
      "file": "@theme_useDarkMode.js",
      "fileHash": "01ec4756",
      "needsInterop": false
    },
    "@theme/useScrollPromise": {
      "src": "../../../../node_modules/@vuepress/theme-default/lib/client/composables/useScrollPromise.js",
      "file": "@theme_useScrollPromise.js",
      "fileHash": "a7178fab",
      "needsInterop": false
    },
    "@theme/useSidebarItems": {
      "src": "../../../../node_modules/@vuepress/theme-default/lib/client/composables/useSidebarItems.js",
      "file": "@theme_useSidebarItems.js",
      "fileHash": "7e010d95",
      "needsInterop": false
    },
    "@theme/useThemeData": {
      "src": "../../../../node_modules/@vuepress/theme-default/lib/client/composables/useThemeData.js",
      "file": "@theme_useThemeData.js",
      "fileHash": "481d342f",
      "needsInterop": false
    },
    "@theme/useUpdateDeviceStatus": {
      "src": "../../../../node_modules/@vuepress/theme-default/lib/client/composables/useUpdateDeviceStatus.js",
      "file": "@theme_useUpdateDeviceStatus.js",
      "fileHash": "86aaf45c",
      "needsInterop": false
    },
    "@theme/useNavbarConfig": {
      "src": "../../../../node_modules/@vuepress/theme-default/lib/client/composables/useNavbarConfig.js",
      "file": "@theme_useNavbarConfig.js",
      "fileHash": "3ff223f6",
      "needsInterop": false
    },
    "@theme/useNavbarRepo": {
      "src": "../../../../node_modules/@vuepress/theme-default/lib/client/composables/useNavbarRepo.js",
      "file": "@theme_useNavbarRepo.js",
      "fileHash": "6fccb46d",
      "needsInterop": false
    },
    "@theme/useNavbarSelectLanguage": {
      "src": "../../../../node_modules/@vuepress/theme-default/lib/client/composables/useNavbarSelectLanguage.js",
      "file": "@theme_useNavbarSelectLanguage.js",
      "fileHash": "c8f4f486",
      "needsInterop": false
    },
    "@theme/useContributors": {
      "src": "../../../../node_modules/@vuepress/theme-default/lib/client/composables/useContributors.js",
      "file": "@theme_useContributors.js",
      "fileHash": "72b6868d",
      "needsInterop": false
    },
    "@theme/useEditLink": {
      "src": "../../../../node_modules/@vuepress/theme-default/lib/client/composables/useEditLink.js",
      "file": "@theme_useEditLink.js",
      "fileHash": "370489fd",
      "needsInterop": false
    },
    "@theme/useLastUpdated": {
      "src": "../../../../node_modules/@vuepress/theme-default/lib/client/composables/useLastUpdated.js",
      "file": "@theme_useLastUpdated.js",
      "fileHash": "6030fdaa",
      "needsInterop": false
    },
    "@theme/useNavigate": {
      "src": "../../../../node_modules/@vuepress/theme-default/lib/client/composables/useNavigate.js",
      "file": "@theme_useNavigate.js",
      "fileHash": "819d031c",
      "needsInterop": false
    },
    "@theme/useRelatedLinks": {
      "src": "../../../../node_modules/@vuepress/theme-default/lib/client/composables/useRelatedLinks.js",
      "file": "@theme_useRelatedLinks.js",
      "fileHash": "c8386769",
      "needsInterop": false
    }
  },
  "chunks": {
    "chunk-UKCZNIRO": {
      "file": "chunk-UKCZNIRO.js"
    },
    "chunk-Y2JKUGW3": {
      "file": "chunk-Y2JKUGW3.js"
    },
    "chunk-VNGGDC5Q": {
      "file": "chunk-VNGGDC5Q.js"
    },
    "chunk-K7GDBC4F": {
      "file": "chunk-K7GDBC4F.js"
    },
    "chunk-U3KLAJNM": {
      "file": "chunk-U3KLAJNM.js"
    },
    "chunk-RY5ODQAQ": {
      "file": "chunk-RY5ODQAQ.js"
    },
    "chunk-S2KHOG74": {
      "file": "chunk-S2KHOG74.js"
    }
  }
}